ic_loss/__init__.py
ic_loss/losses.py
ic_loss/models.py
ic_loss-1.0.1.dist-info/LICENSE
ic_loss-1.0.1.dist-info/METADATA
ic_loss-1.0.1.dist-info/WHEEL
ic_loss-1.0.1.dist-info/top_level.txt
ic_loss-1.0.1.dist-info/RECORD
