Metadata-Version: 2.1
Name: ic-loss
Version: 1.0.1
Summary: Implementation of inverse contrastive loss
Home-page: https://github.com/novice03/ic-loss
Author: Pranav Pulijala
License: UNKNOWN
Platform: UNKNOWN
Classifier: Programming Language :: Python :: 3
Classifier: Operating System :: OS Independent
